mindcraft/__init__.py
mindcraft/settings.py
mindcraft/features/__init__.py
mindcraft/features/mood.py
mindcraft/features/motivation.py
mindcraft/features/personality.py
mindcraft/infra/__init__.py
mindcraft/infra/embeddings/__init__.py
mindcraft/infra/embeddings/embeddings_types.py
mindcraft/infra/engine/__init__.py
mindcraft/infra/engine/llm.py
mindcraft/infra/engine/llm_types.py
mindcraft/infra/engine/local_llm.py
mindcraft/infra/engine/local_vllm.py
mindcraft/infra/engine/remote_vllm.py
mindcraft/infra/engine/serving/__init__.py
mindcraft/infra/prompts/__init__.py
mindcraft/infra/prompts/prompt.py
mindcraft/infra/prompts/templates/__init__.py
mindcraft/infra/prompts/templates/prompt_template.py
mindcraft/infra/sft/__init__.py
mindcraft/infra/sft/feedback.py
mindcraft/infra/splitters/__init__.py
mindcraft/infra/splitters/sentence_text_splitter.py
mindcraft/infra/splitters/text_splitter.py
mindcraft/infra/splitters/text_splitters_types.py
mindcraft/infra/splitters/token_text_splitter.py
mindcraft/infra/splitters/tokenizer.py
mindcraft/infra/vectorstore/__init__.py
mindcraft/infra/vectorstore/chroma.py
mindcraft/infra/vectorstore/search_results.py
mindcraft/infra/vectorstore/store.py
mindcraft/infra/vectorstore/stores_types.py
mindcraft/lore/__init__.py
mindcraft/lore/world.py
mindcraft/memory/__init__.py
mindcraft/memory/ltm.py
mindcraft/memory/stm.py
mindcraft/memory/summarizer_types.py
mindcraft/mind/__init__.py
mindcraft/mind/npc.py
mindcraft/styles/__init__.py
mindcraft/styles/conversational_style.py
mindcraft-0.2.4.dist-info/LICENSE
mindcraft-0.2.4.dist-info/METADATA
mindcraft-0.2.4.dist-info/WHEEL
mindcraft-0.2.4.dist-info/top_level.txt
mindcraft-0.2.4.dist-info/RECORD
