Metadata-Version: 2.1
Name: mindcraft
Version: 0.2.4
Summary: Mindcraft: an LLM-based engine for creating real NPCs. Empowered by Hugging Face, quantized LLMs with AWQ (thanks @TheBloke) and vLLM. It follows a RAG approach with chunk or sentence splitting, and a vector store. Right now, ChromaDB is the supported Vector Store and chunk splitting using `tiktoken` or sentence splitting using `spacy` are available.
Home-page: https://github.com/josejuanmartinez/mindcraft
Download-URL: https://github.com/josejuanmartinez/mindcraft
Author: Juan.Martinez
Author-email: jjmcarrascosa@gmail.com
License: MIT
Keywords: nlp,llm,npc,conversations,videogames
Classifier: Development Status :: 2 - Pre-Alpha
Classifier: Environment :: Console
Classifier: Natural Language :: English
Classifier: Operating System :: OS Independent
Classifier: Programming Language :: Python :: 3.10
Classifier: Programming Language :: Python :: 3.11
Classifier: Environment :: GPU :: NVIDIA CUDA :: 12 :: 12.1
Classifier: Topic :: Scientific/Engineering :: Artificial Intelligence
Classifier: Topic :: Games/Entertainment
Requires-Python: >=3.10.0
License-File: LICENSE
Requires-Dist: transformers ==4.36.2
Requires-Dist: sentence-transformers ==2.2.2
Requires-Dist: autoawq ==0.1.8
Requires-Dist: requests ~=2.31.0
Requires-Dist: torch ==2.1.2
